mock_ads_mcp/__init__.py
mock_ads_mcp-0.1.2.dist-info/METADATA
mock_ads_mcp-0.1.2.dist-info/WHEEL
mock_ads_mcp-0.1.2.dist-info/entry_points.txt
mock_ads_mcp-0.1.2.dist-info/RECORD
