Metadata-Version: 2.4
Name: mock-ads-mcp
Version: 0.1.2
Summary: A test MCP server for ads campaign management
Author-email: Xingjian Guo <guoxj@oasalife.com>
Requires-Python: >=3.10
Requires-Dist: fastmcp>=2.3.3
Requires-Dist: pydantic>=2.11.4
